{
  "dataset_revision": "4d8694f8f0e0100860b497b999b3dbed754a0513",
  "task_name": "STS16",
  "mteb_version": "1.38.33",
  "scores": {
    "test": [
      {
        "pearson": 0.630438,
        "spearman": 0.675883,
        "cosine_pearson": 0.630438,
        "cosine_spearman": 0.675883,
        "manhattan_pearson": 0.717479,
        "manhattan_spearman": 0.727136,
        "euclidean_pearson": 0.714526,
        "euclidean_spearman": 0.724774,
        "main_score": 0.675883,
        "hf_subset": "default",
        "languages": [
          "eng-Latn"
        ]
      }
    ]
  },
  "evaluation_time": 1.8155674934387207,
  "kg_co2_emissions": null
}